kaolin/_C.so
kaolin/__init__.py
kaolin/version.py
kaolin/csrc/bindings.cpp
kaolin/csrc/metrics/sided_distance.cpp
kaolin/csrc/metrics/sided_distance_cuda.cu
kaolin/csrc/metrics/unbatched_triangle_distance.cpp
kaolin/csrc/metrics/unbatched_triangle_distance_cuda.cu
kaolin/csrc/ops/packed_simple_sum.cpp
kaolin/csrc/ops/packed_simple_sum_cuda.cu
kaolin/csrc/ops/tile_to_packed.cpp
kaolin/csrc/ops/tile_to_packed_cuda.cu
kaolin/csrc/ops/conversions/mesh_to_spc/mesh_to_spc.cpp
kaolin/csrc/ops/conversions/mesh_to_spc/mesh_to_spc_cuda.cu
kaolin/csrc/ops/conversions/unbatched_mcube/unbatched_mcube.cpp
kaolin/csrc/ops/conversions/unbatched_mcube/unbatched_mcube_cuda.cu
kaolin/csrc/ops/mesh/mesh_intersection.cpp
kaolin/csrc/ops/mesh/mesh_intersection_cuda.cu
kaolin/csrc/ops/spc/convolution.cpp
kaolin/csrc/ops/spc/convolution_cuda.cu
kaolin/csrc/ops/spc/feature_grids.cpp
kaolin/csrc/ops/spc/feature_grids_cuda.cu
kaolin/csrc/ops/spc/generate_points.cu
kaolin/csrc/ops/spc/minkowski_conv.cu
kaolin/csrc/ops/spc/point_utils.cpp
kaolin/csrc/ops/spc/point_utils_cuda.cu
kaolin/csrc/ops/spc/query.cpp
kaolin/csrc/ops/spc/query_cuda.cu
kaolin/csrc/ops/spc/scan_octrees.cu
kaolin/csrc/ops/spc/spc.cpp
kaolin/csrc/render/mesh/deftet.cpp
kaolin/csrc/render/mesh/deftet_cuda.cu
kaolin/csrc/render/mesh/dibr_soft_mask.cpp
kaolin/csrc/render/mesh/dibr_soft_mask_cuda.cu
kaolin/csrc/render/mesh/rasterization.cpp
kaolin/csrc/render/mesh/rasterization_cuda.cu
kaolin/csrc/render/spc/raytrace.cpp
kaolin/csrc/render/spc/raytrace_cuda.cu
kaolin/cython/ops/conversions/mise.cpp
kaolin/cython/ops/mesh/triangle_hash.cpp
kaolin/experimental/dash3d/kaolin-dash3d
kaolin/experimental/dash3d/static/core-min.js
kaolin/experimental/dash3d/static/favicon.ico
kaolin/experimental/dash3d/static/green_plastic.frag
kaolin/experimental/dash3d/static/style.css
kaolin/experimental/dash3d/static/thirdparty.css
kaolin/experimental/dash3d/static/thirdparty.js
kaolin/experimental/dash3d/templates/home.html
kaolin-0.11.0.dist-info/LICENSE
kaolin-0.11.0.dist-info/METADATA
kaolin-0.11.0.dist-info/WHEEL
kaolin-0.11.0.dist-info/top_level.txt
kaolin-0.11.0.dist-info/RECORD
