Metadata-Version: 2.1
Name: kaolin
Version: 0.11.0
Summary: Kaolin: A PyTorch library for accelerating 3D deep learning research
Home-page: https://github.com/NVIDIAGameWorks/kaolin
Author: NVIDIA
License: Apache License 2.0
Platform: UNKNOWN
Requires-Python: ~=3.7
Requires-Dist: scipy (<=1.5.2,>=1.2.0)
Requires-Dist: Pillow (>=8.0.0)
Requires-Dist: tqdm (>=4.51.0)
Requires-Dist: tornado (==6.1)
Requires-Dist: flask (==2.0.3)
Requires-Dist: usd-core (>=20.11) ; python_version < "3.10"
